<annotation>
	<folder>allimages</folder>
	<filename>0085.png</filename>
	<path>/Users/dobby/Documents/arcticfo111/msaischool_23/real_time_facemask_detection/RealTimeObjectDetection/Tensorflow/workspace/images/allimages/0085.png</path>
	<source>
		<database>Unknown</database>
	</source>
	<size>
		<width>522</width>
		<height>408</height>
		<depth>3</depth>
	</size>
	<segmented>0</segmented>
	<object>
		<name>Mask</name>
		<pose>Unspecified</pose>
		<truncated>0</truncated>
		<difficult>0</difficult>
		<bndbox>
			<xmin>201</xmin>
			<ymin>150</ymin>
			<xmax>238</xmax>
			<ymax>171</ymax>
		</bndbox>
	</object>
</annotation>
